crabnet/__init__.py
crabnet/crabnet_.py
crabnet/kingcrab.py
crabnet/meta.yaml
crabnet/data/__init__.py
crabnet/data/get_dataset_size.py
crabnet/data/benchmark_data/__init__.py
crabnet/data/benchmark_data/CritExam__Ed/__init__.py
crabnet/data/benchmark_data/CritExam__Ed/test.csv
crabnet/data/benchmark_data/CritExam__Ed/train.csv
crabnet/data/benchmark_data/CritExam__Ed/val.csv
crabnet/data/benchmark_data/CritExam__Ef/__init__.py
crabnet/data/benchmark_data/CritExam__Ef/test.csv
crabnet/data/benchmark_data/CritExam__Ef/train.csv
crabnet/data/benchmark_data/CritExam__Ef/val.csv
crabnet/data/benchmark_data/OQMD_Bandgap/__init__.py
crabnet/data/benchmark_data/OQMD_Bandgap/test.csv
crabnet/data/benchmark_data/OQMD_Bandgap/train.csv
crabnet/data/benchmark_data/OQMD_Bandgap/val.csv
crabnet/data/benchmark_data/OQMD_Energy_per_atom/__init__.py
crabnet/data/benchmark_data/OQMD_Energy_per_atom/test.csv
crabnet/data/benchmark_data/OQMD_Energy_per_atom/train.csv
crabnet/data/benchmark_data/OQMD_Energy_per_atom/val.csv
crabnet/data/benchmark_data/OQMD_Formation_Enthalpy/__init__.py
crabnet/data/benchmark_data/OQMD_Formation_Enthalpy/test.csv
crabnet/data/benchmark_data/OQMD_Formation_Enthalpy/train.csv
crabnet/data/benchmark_data/OQMD_Formation_Enthalpy/val.csv
crabnet/data/benchmark_data/OQMD_Volume_per_atom/__init__.py
crabnet/data/benchmark_data/OQMD_Volume_per_atom/test.csv
crabnet/data/benchmark_data/OQMD_Volume_per_atom/train.csv
crabnet/data/benchmark_data/OQMD_Volume_per_atom/val.csv
crabnet/data/benchmark_data/aflow__Egap/__init__.py
crabnet/data/benchmark_data/aflow__Egap/test.csv
crabnet/data/benchmark_data/aflow__Egap/train.csv
crabnet/data/benchmark_data/aflow__Egap/val.csv
crabnet/data/benchmark_data/aflow__ael_bulk_modulus_vrh/__init__.py
crabnet/data/benchmark_data/aflow__ael_bulk_modulus_vrh/test.csv
crabnet/data/benchmark_data/aflow__ael_bulk_modulus_vrh/train.csv
crabnet/data/benchmark_data/aflow__ael_bulk_modulus_vrh/val.csv
crabnet-2.0.8.dist-info/LICENSE
crabnet-2.0.8.dist-info/WHEEL
crabnet-2.0.8.dist-info/METADATA
crabnet-2.0.8.dist-info/RECORD
