Metadata-Version: 2.1
Name: crabnet
Version: 2.0.8
Summary: Predict materials properties using only the composition information.
Author: Kaai Kauwe
Author-email: Anthony Yu-Tung Wang <aytwang@alumni.uwaterloo.ca>, "Sterling G. Baird" <sterling.baird@utah.edu>
Requires-Python: >=3.7,<3.11
Classifier: License :: OSI Approved :: MIT License
Classifier: Programming Language :: Python :: 3.7
Classifier: Programming Language :: Python :: 3.8
Classifier: Programming Language :: Python :: 3.9
Classifier: Operating System :: OS Independent
Requires-Dist: numpy
Requires-Dist: pandas
Requires-Dist: scikit-learn
Requires-Dist: scipy
Requires-Dist: matplotlib
Requires-Dist: seaborn
Requires-Dist: tqdm
Requires-Dist: colorama
Requires-Dist: joblib
Requires-Dist: psutil
Requires-Dist: pytest ; extra == "test"
Requires-Dist: pytest-cov ; extra == "test"
Requires-Dist: pre-commit ; extra == "test"
Requires-Dist: sphinx==4.2.0 ; extra == "test"
Requires-Dist: myst-parser==0.15.2 ; extra == "test"
Requires-Dist: sphinx_rtd_theme ; extra == "test"
Requires-Dist: nbformat >=4.2.0 ; extra == "test"
Requires-Dist: black >=22.1.0 ; extra == "test"
Requires-Dist: conda-souschef ; extra == "test"
Requires-Dist: matbench ; extra == "test"
Project-URL: Home, https://github.com/sparks-baird/CrabNet
Provides-Extra: test
